Workbook
Name Title1: CashFlow[[#Headers],[Cash Flow]]
Name Title2: Income[[#Headers],[Monthly Income]]
Name Title3: Expenses[[#Headers],[Monthly expenses]]

Sheet Cash flow
C3: Year | E3: 2025
C4: Tot BUDGET
C8: Cash Flow | D8: Actual
C9: Total income | D9: ='Yearly income'!D10 -> 0
C10: Total expenses | D10: =Expenses[[#Totals],[Actual]] -> 0
C11: Evaluated Bank Amout | D11: =D9-D10 -> 0
D21: ='Yearly income'!$D$27 - 'Yearly expenses'!$D$42 -> 0
D22: ='Yearly income'!$D$38 - 'Yearly expenses'!$D$63 -> 0
D23: ='Yearly income'!$D$49 - 'Yearly expenses'!$D$84 -> 0
D24: ='Yearly income'!$D$60 - 'Yearly expenses'!$D$105 -> 0
D25: ='Yearly income'!$D$71 - 'Yearly expenses'!$D$126 -> 0
D26: ='Yearly income'!$D$82 - 'Yearly expenses'!$D$147 -> 0
D27: ='Yearly income'!$D$93 - 'Yearly expenses'!$D$168 -> 0
D28: ='Yearly income'!$D$104 - 'Yearly expenses'!$D$189 -> 0
D29: ='Yearly income'!$D$115 - 'Yearly expenses'!$D$210 -> 0
D30: ='Yearly income'!$D$126 - 'Yearly expenses'!$D$231 -> 0
D31: ='Yearly income'!$D$137 - 'Yearly expenses'!$D$252 -> 0
D32: ='Yearly income'!$D$148 - 'Yearly expenses'!$D$273 -> 0

Sheet Yearly income
C10: Yearly INCOME | D10: =SUM(D11:D15) -> 0
C11: PoliMi | D11: =SUM(D23+D34+D45) -> 0
C12: Deddo | D12: =SUM(D24+D35+D46) -> 0
C13: Other income | D13: =SUM(D25+D36+D47) -> 0
C14: Cash | D14: =SUM(D26+D37+D48) -> 0
C15: Init | D15: 0
C20: Janaury INCOME
C22: Monthly Income | D22: Actual
C23: PoliMi | D23: =SUMIFS('List Income'!$C$3:$C$100000, 'List Income'!$B$3:$B$100000, 'Yearly income'!$C11, 'List Income'!$A$3:$A$100000, ">=" & DATE('Cash flow'!$E$3, 1, 1), 'List Income'!$A$3:$A$100000, "<" & DATE('Cash flow'!$E$3, 2, 1)) -> 0
C24: Deddo | D24: =SUMIFS('List Income'!$C$3:$C$100000, 'List Income'!$B$3:$B$100000, 'Yearly income'!$C12, 'List Income'!$A$3:$A$100000, ">=" & DATE('Cash flow'!$E$3, 1, 1), 'List Income'!$A$3:$A$100000, "<" & DATE('Cash flow'!$E$3, 2, 1)) -> 0
C25: Other Income | D25: =SUMIFS('List Income'!$C$3:$C$100000, 'List Income'!$B$3:$B$100000, 'Yearly income'!$C13, 'List Income'!$A$3:$A$100000, ">=" & DATE('Cash flow'!$E$3, 1, 1), 'List Income'!$A$3:$A$100000, "<" & DATE('Cash flow'!$E$3, 2, 1)) -> 0
C26: Cash | D26: =SUMIFS('List Income'!$C$3:$C$100000, 'List Income'!$B$3:$B$100000, 'Yearly income'!$C14, 'List Income'!$A$3:$A$100000, ">=" & DATE('Cash flow'!$E$3, 1, 1), 'List Income'!$A$3:$A$100000, "<" & DATE('Cash flow'!$E$3, 2, 1)) -> 0
C27: Total Income | D27: =SUBTOTAL(109,Income[Actual]) -> 0
C31: February INCOME
C33: Monthly Income | D33: Actual
C34: PoliMi | D34: =SUMIFS('List Income'!$C$3:$C$100000, 'List Income'!$B$3:$B$100000, 'Yearly income'!$C11, 'List Income'!$A$3:$A$100000, ">=" & DATE('Cash flow'!$E$3, 2, 1), 'List Income'!$A$3:$A$100000, "<" & DATE('Cash flow'!$E$3, 3, 1)) -> 0
C35: Deddo | D35: =SUMIFS('List Income'!$C$3:$C$100000, 'List Income'!$B$3:$B$100000, 'Yearly income'!$C12, 'List Income'!$A$3:$A$100000, ">=" & DATE('Cash flow'!$E$3, 2, 1), 'List Income'!$A$3:$A$100000, "<" & DATE('Cash flow'!$E$3, 3, 1)) -> 0
C36: Other Income | D36: =SUMIFS('List Income'!$C$3:$C$100000, 'List Income'!$B$3:$B$100000, 'Yearly income'!$C13, 'List Income'!$A$3:$A$100000, ">=" & DATE('Cash flow'!$E$3, 2, 1), 'List Income'!$A$3:$A$100000, "<" & DATE('Cash flow'!$E$3, 3, 1)) -> 0
C37: Cash | D37: =SUMIFS('List Income'!$C$3:$C$100000, 'List Income'!$B$3:$B$100000, 'Yearly income'!$C14, 'List Income'!$A$3:$A$100000, ">=" & DATE('Cash flow'!$E$3, 2, 1), 'List Income'!$A$3:$A$100000, "<" & DATE('Cash flow'!$E$3, 3, 1)) -> 0
C38: Total Income | D38: =SUBTOTAL(109,Income18[Actual]) -> 0
C42: March INCOME
C44: Monthly Income | D44: Actual
C45: PoliMi | D45: =SUMIFS('List Income'!$C$3:$C$100000, 'List Income'!$B$3:$B$100000, 'Yearly income'!$C11, 'List Income'!$A$3:$A$100000, ">=" & DATE('Cash flow'!$E$3, 3, 1), 'List Income'!$A$3:$A$100000, "<" & DATE('Cash flow'!$E$3, 4, 1)) -> 0
C46: Deddo | D46: =SUMIFS('List Income'!$C$3:$C$100000, 'List Income'!$B$3:$B$100000, 'Yearly income'!$C12, 'List Income'!$A$3:$A$100000, ">=" & DATE('Cash flow'!$E$3, 3, 1), 'List Income'!$A$3:$A$100000, "<" & DATE('Cash flow'!$E$3, 4, 1)) -> 0
C47: Other Income | D47: =SUMIFS('List Income'!$C$3:$C$100000, 'List Income'!$B$3:$B$100000, 'Yearly income'!$C13, 'List Income'!$A$3:$A$100000, ">=" & DATE('Cash flow'!$E$3, 3, 1), 'List Income'!$A$3:$A$100000, "<" & DATE('Cash flow'!$E$3, 4, 1)) -> 0
C48: Cash | D48: =SUMIFS('List Income'!$C$3:$C$100000, 'List Income'!$B$3:$B$100000, 'Yearly income'!$C14, 'List Income'!$A$3:$A$100000, ">=" & DATE('Cash flow'!$E$3, 3, 1), 'List Income'!$A$3:$A$100000, "<" & DATE('Cash flow'!$E$3, 4, 1)) -> 0
C49: Total Income | D49: =SUBTOTAL(109,Income19[Actual]) -> 0
C53: April INCOME
C55: Monthly Income | D55: Actual
C56: PoliMi | D56: =SUMIFS('List Income'!$C$3:$C$100000, 'List Income'!$B$3:$B$100000, 'Yearly income'!$C22, 'List Income'!$A$3:$A$100000, ">=" & DATE('Cash flow'!$E$3, 4, 1), 'List Income'!$A$3:$A$100000, "<" & DATE('Cash flow'!$E$3, 5, 1)) -> 0
C57: Deddo | D57: =SUMIFS('List Income'!$C$3:$C$100000, 'List Income'!$B$3:$B$100000, 'Yearly income'!$C23, 'List Income'!$A$3:$A$100000, ">=" & DATE('Cash flow'!$E$3, 4, 1), 'List Income'!$A$3:$A$100000, "<" & DATE('Cash flow'!$E$3, 5, 1)) -> 0
C58: Other Income | D58: =SUMIFS('List Income'!$C$3:$C$100000, 'List Income'!$B$3:$B$100000, 'Yearly income'!$C24, 'List Income'!$A$3:$A$100000, ">=" & DATE('Cash flow'!$E$3, 4, 1), 'List Income'!$A$3:$A$100000, "<" & DATE('Cash flow'!$E$3, 5, 1)) -> 0
C59: Cash | D59: =SUMIFS('List Income'!$C$3:$C$100000, 'List Income'!$B$3:$B$100000, 'Yearly income'!$C25, 'List Income'!$A$3:$A$100000, ">=" & DATE('Cash flow'!$E$3, 4, 1), 'List Income'!$A$3:$A$100000, "<" & DATE('Cash flow'!$E$3, 5, 1)) -> 0
C60: Total Income | D60: =SUBTOTAL(109,Income197[Actual]) -> 0
C64: May INCOME
C66: Monthly Income | D66: Actual
C67: PoliMi | D67: =SUMIFS('List Income'!$C$3:$C$100000, 'List Income'!$B$3:$B$100000, 'Yearly income'!$C33, 'List Income'!$A$3:$A$100000, ">=" & DATE('Cash flow'!$E$3, 5, 1), 'List Income'!$A$3:$A$100000, "<" & DATE('Cash flow'!$E$3, 6, 1)) -> 0
C68: Deddo | D68: =SUMIFS('List Income'!$C$3:$C$100000, 'List Income'!$B$3:$B$100000, 'Yearly income'!$C34, 'List Income'!$A$3:$A$100000, ">=" & DATE('Cash flow'!$E$3, 5, 1), 'List Income'!$A$3:$A$100000, "<" & DATE('Cash flow'!$E$3, 6, 1)) -> 0
C69: Other Income | D69: =SUMIFS('List Income'!$C$3:$C$100000, 'List Income'!$B$3:$B$100000, 'Yearly income'!$C35, 'List Income'!$A$3:$A$100000, ">=" & DATE('Cash flow'!$E$3, 5, 1), 'List Income'!$A$3:$A$100000, "<" & DATE('Cash flow'!$E$3, 6, 1)) -> 0
C70: Cash | D70: =SUMIFS('List Income'!$C$3:$C$100000, 'List Income'!$B$3:$B$100000, 'Yearly income'!$C36, 'List Income'!$A$3:$A$100000, ">=" & DATE('Cash flow'!$E$3, 5, 1), 'List Income'!$A$3:$A$100000, "<" & DATE('Cash flow'!$E$3, 6, 1)) -> 0
C71: Total Income | D71: =SUBTOTAL(109,Income1978[Actual]) -> 0
C75: June INCOME
C77: Monthly Income | D77: Actual
C78: PoliMi | D78: =SUMIFS('List Income'!$C$3:$C$100000, 'List Income'!$B$3:$B$100000, 'Yearly income'!$C44, 'List Income'!$A$3:$A$100000, ">=" & DATE('Cash flow'!$E$3, 6, 1), 'List Income'!$A$3:$A$100000, "<" & DATE('Cash flow'!$E$3, 7, 1)) -> 0
C79: Deddo | D79: =SUMIFS('List Income'!$C$3:$C$100000, 'List Income'!$B$3:$B$100000, 'Yearly income'!$C45, 'List Income'!$A$3:$A$100000, ">=" & DATE('Cash flow'!$E$3, 6, 1), 'List Income'!$A$3:$A$100000, "<" & DATE('Cash flow'!$E$3, 7, 1)) -> 0
C80: Other Income | D80: =SUMIFS('List Income'!$C$3:$C$100000, 'List Income'!$B$3:$B$100000, 'Yearly income'!$C46, 'List Income'!$A$3:$A$100000, ">=" & DATE('Cash flow'!$E$3, 6, 1), 'List Income'!$A$3:$A$100000, "<" & DATE('Cash flow'!$E$3, 7, 1)) -> 0
C81: Cash | D81: =SUMIFS('List Income'!$C$3:$C$100000, 'List Income'!$B$3:$B$100000, 'Yearly income'!$C47, 'List Income'!$A$3:$A$100000, ">=" & DATE('Cash flow'!$E$3, 6, 1), 'List Income'!$A$3:$A$100000, "<" & DATE('Cash flow'!$E$3, 7, 1)) -> 0
C82: Total Income | D82: =SUBTOTAL(109,Income1979[Actual]) -> 0
C86: July INCOME
C88: Monthly Income | D88: Actual
C89: PoliMi | D89: =SUMIFS('List Income'!$C$3:$C$100000, 'List Income'!$B$3:$B$100000, 'Yearly income'!$C55, 'List Income'!$A$3:$A$100000, ">=" & DATE('Cash flow'!$E$3, 7, 1), 'List Income'!$A$3:$A$100000, "<" & DATE('Cash flow'!$E$3, 8, 1)) -> 0
C90: Deddo | D90: =SUMIFS('List Income'!$C$3:$C$100000, 'List Income'!$B$3:$B$100000, 'Yearly income'!$C56, 'List Income'!$A$3:$A$100000, ">=" & DATE('Cash flow'!$E$3, 7, 1), 'List Income'!$A$3:$A$100000, "<" & DATE('Cash flow'!$E$3, 8, 1)) -> 0
C91: Other Income | D91: =SUMIFS('List Income'!$C$3:$C$100000, 'List Income'!$B$3:$B$100000, 'Yearly income'!$C57, 'List Income'!$A$3:$A$100000, ">=" & DATE('Cash flow'!$E$3, 7, 1), 'List Income'!$A$3:$A$100000, "<" & DATE('Cash flow'!$E$3, 8, 1)) -> 0
C92: Cash | D92: =SUMIFS('List Income'!$C$3:$C$100000, 'List Income'!$B$3:$B$100000, 'Yearly income'!$C58, 'List Income'!$A$3:$A$100000, ">=" & DATE('Cash flow'!$E$3, 7, 1), 'List Income'!$A$3:$A$100000, "<" & DATE('Cash flow'!$E$3, 8, 1)) -> 0
C93: Total Income | D93: =SUBTOTAL(109,Income19711[Actual]) -> 0
C97: August INCOME
C99: Monthly Income | D99: Actual
C100: PoliMi | D100: =SUMIFS('List Income'!$C$3:$C$100000, 'List Income'!$B$3:$B$100000, 'Yearly income'!$C66, 'List Income'!$A$3:$A$100000, ">=" & DATE('Cash flow'!$E$3, 8, 1), 'List Income'!$A$3:$A$100000, "<" & DATE('Cash flow'!$E$3, 9, 1)) -> 0
C101: Deddo | D101: =SUMIFS('List Income'!$C$3:$C$100000, 'List Income'!$B$3:$B$100000, 'Yearly income'!$C67, 'List Income'!$A$3:$A$100000, ">=" & DATE('Cash flow'!$E$3, 8, 1), 'List Income'!$A$3:$A$100000, "<" & DATE('Cash flow'!$E$3, 9, 1)) -> 0
C102: Other Income | D102: =SUMIFS('List Income'!$C$3:$C$100000, 'List Income'!$B$3:$B$100000, 'Yearly income'!$C68, 'List Income'!$A$3:$A$100000, ">=" & DATE('Cash flow'!$E$3, 8, 1), 'List Income'!$A$3:$A$100000, "<" & DATE('Cash flow'!$E$3, 9, 1)) -> 0
C103: Cash | D103: =SUMIFS('List Income'!$C$3:$C$100000, 'List Income'!$B$3:$B$100000, 'Yearly income'!$C69, 'List Income'!$A$3:$A$100000, ">=" & DATE('Cash flow'!$E$3, 8, 1), 'List Income'!$A$3:$A$100000, "<" & DATE('Cash flow'!$E$3, 9, 1)) -> 0
C104: Total Income | D104: =SUBTOTAL(109,Income19712[Actual]) -> 0
C108: September INCOME
C110: Monthly Income | D110: Actual
C111: PoliMi | D111: =SUMIFS('List Income'!$C$3:$C$100000, 'List Income'!$B$3:$B$100000, 'Yearly income'!$C77, 'List Income'!$A$3:$A$100000, ">=" & DATE('Cash flow'!$E$3, 9, 1), 'List Income'!$A$3:$A$100000, "<" & DATE('Cash flow'!$E$3, 10, 1)) -> 0
C112: Deddo | D112: =SUMIFS('List Income'!$C$3:$C$100000, 'List Income'!$B$3:$B$100000, 'Yearly income'!$C78, 'List Income'!$A$3:$A$100000, ">=" & DATE('Cash flow'!$E$3, 9, 1), 'List Income'!$A$3:$A$100000, "<" & DATE('Cash flow'!$E$3, 10, 1)) -> 0
C113: Other Income | D113: =SUMIFS('List Income'!$C$3:$C$100000, 'List Income'!$B$3:$B$100000, 'Yearly income'!$C79, 'List Income'!$A$3:$A$100000, ">=" & DATE('Cash flow'!$E$3, 9, 1), 'List Income'!$A$3:$A$100000, "<" & DATE('Cash flow'!$E$3, 10, 1)) -> 0
C114: Cash | D114: =SUMIFS('List Income'!$C$3:$C$100000, 'List Income'!$B$3:$B$100000, 'Yearly income'!$C80, 'List Income'!$A$3:$A$100000, ">=" & DATE('Cash flow'!$E$3, 9, 1), 'List Income'!$A$3:$A$100000, "<" & DATE('Cash flow'!$E$3, 10, 1)) -> 0
C115: Total Income | D115: =SUBTOTAL(109,Income19713[Actual]) -> 0
C119: October INCOME
C121: Monthly Income | D121: Actual
C122: PoliMi | D122: =SUMIFS('List Income'!$C$3:$C$100000, 'List Income'!$B$3:$B$100000, 'Yearly income'!$C88, 'List Income'!$A$3:$A$100000, ">=" & DATE('Cash flow'!$E$3, 10, 1), 'List Income'!$A$3:$A$100000, "<" & DATE('Cash flow'!$E$3, 11, 1)) -> 0
C123: Deddo | D123: =SUMIFS('List Income'!$C$3:$C$100000, 'List Income'!$B$3:$B$100000, 'Yearly income'!$C89, 'List Income'!$A$3:$A$100000, ">=" & DATE('Cash flow'!$E$3, 10, 1), 'List Income'!$A$3:$A$100000, "<" & DATE('Cash flow'!$E$3, 11, 1)) -> 0
C124: Other Income | D124: =SUMIFS('List Income'!$C$3:$C$100000, 'List Income'!$B$3:$B$100000, 'Yearly income'!$C90, 'List Income'!$A$3:$A$100000, ">=" & DATE('Cash flow'!$E$3, 10, 1), 'List Income'!$A$3:$A$100000, "<" & DATE('Cash flow'!$E$3, 11, 1)) -> 0
C125: Cash | D125: =SUMIFS('List Income'!$C$3:$C$100000, 'List Income'!$B$3:$B$100000, 'Yearly income'!$C91, 'List Income'!$A$3:$A$100000, ">=" & DATE('Cash flow'!$E$3, 10, 1), 'List Income'!$A$3:$A$100000, "<" & DATE('Cash flow'!$E$3, 11, 1)) -> 0
C126: Total Income | D126: =SUBTOTAL(109,Income19714[Actual]) -> 0
C130: November INCOME
C132: Monthly Income | D132: Actual
C133: PoliMi | D133: =SUMIFS('List Income'!$C$3:$C$100000, 'List Income'!$B$3:$B$100000, 'Yearly income'!$C99, 'List Income'!$A$3:$A$100000, ">=" & DATE('Cash flow'!$E$3, 11, 1), 'List Income'!$A$3:$A$100000, "<" & DATE('Cash flow'!$E$3, 12, 1)) -> 0
C134: Deddo | D134: =SUMIFS('List Income'!$C$3:$C$100000, 'List Income'!$B$3:$B$100000, 'Yearly income'!$C100, 'List Income'!$A$3:$A$100000, ">=" & DATE('Cash flow'!$E$3, 11, 1), 'List Income'!$A$3:$A$100000, "<" & DATE('Cash flow'!$E$3, 12, 1)) -> 0
C135: Other Income | D135: =SUMIFS('List Income'!$C$3:$C$100000, 'List Income'!$B$3:$B$100000, 'Yearly income'!$C101, 'List Income'!$A$3:$A$100000, ">=" & DATE('Cash flow'!$E$3, 11, 1), 'List Income'!$A$3:$A$100000, "<" & DATE('Cash flow'!$E$3, 12, 1)) -> 0
C136: Cash | D136: =SUMIFS('List Income'!$C$3:$C$100000, 'List Income'!$B$3:$B$100000, 'Yearly income'!$C102, 'List Income'!$A$3:$A$100000, ">=" & DATE('Cash flow'!$E$3, 11, 1), 'List Income'!$A$3:$A$100000, "<" & DATE('Cash flow'!$E$3, 12, 1)) -> 0
C137: Total Income | D137: =SUBTOTAL(109,Income19715[Actual]) -> 0
C141: December INCOME
C143: Monthly Income | D143: Actual
C144: PoliMi | D144: =SUMIFS('List Income'!$C$3:$C$100000, 'List Income'!$B$3:$B$100000, 'Yearly income'!$C110, 'List Income'!$A$3:$A$100000, ">=" & DATE('Cash flow'!$E$3, 12, 1), 'List Income'!$A$3:$A$100000, "<" & DATE('Cash flow'!$E$3+1, 1, 1)) -> 0
C145: Deddo | D145: =SUMIFS('List Income'!$C$3:$C$100000, 'List Income'!$B$3:$B$100000, 'Yearly income'!$C111, 'List Income'!$A$3:$A$100000, ">=" & DATE('Cash flow'!$E$3, 12, 1), 'List Income'!$A$3:$A$100000, "<" & DATE('Cash flow'!$E$3+1, 1, 1)) -> 0
C146: Other Income | D146: =SUMIFS('List Income'!$C$3:$C$100000, 'List Income'!$B$3:$B$100000, 'Yearly income'!$C112, 'List Income'!$A$3:$A$100000, ">=" & DATE('Cash flow'!$E$3, 12, 1), 'List Income'!$A$3:$A$100000, "<" & DATE('Cash flow'!$E$3+1, 1, 1)) -> 0
C147: Cash | D147: =SUMIFS('List Income'!$C$3:$C$100000, 'List Income'!$B$3:$B$100000, 'Yearly income'!$C113, 'List Income'!$A$3:$A$100000, ">=" & DATE('Cash flow'!$E$3, 12, 1), 'List Income'!$A$3:$A$100000, "<" & DATE('Cash flow'!$E$3+1, 1, 1)) -> 0
C148: Total Income | D148: =SUBTOTAL(109,Income19716[Actual]) -> 0

Sheet Yearly expenses
C3: Yearly EXPENSES
C5: Monthly expenses | D5: Actual
C6: Restaurants | D6: =SUM(D28+D49+D70) -> 0
C7: Groceries | D7: =SUM(D29+D50+D71) -> 0
C8: Pre-paid card | D8: =SUM(D30+D51+D72) -> 0
C9: Going out | D9: =SUM(D31+D52+D73) -> 0
C10: Claudia | D10: =SUM(D32+D53+D74) -> 0
C11: Family | D11: =SUM(D33+D54+D75) -> 0
C12: Shopping | D12: =SUM(D34+D55+D76) -> 0
C13: Transportation | D13: =SUM(D35+D56+D77) -> 0
C14: Personal care | D14: =SUM(D36+D57+D78) -> 0
C15: Credit cards | D15: =SUM(D37+D58+D79) -> 0
C16: Gifts / Charity | D16: =SUM(D38+D59+D80) -> 0
C17: Travel | D17: =SUM(D39+D60+D81) -> 0
... C19: Other | D19: =SUM(D41+D62+D83) -> 0
C20: Total expenses | D20: =SUBTOTAL(109,Expenses[Actual]) -> 0
C25: January EXPENSES
C27: Monthly expenses | D27: Actual
C28: Restaurants | D28: =SUMIFS('List Expenses'!$C$3:$C$100000, 'List Expenses'!$B$3:$B$100000, 'Yearly expenses'!$C6, 'List Expenses'!$A$3:$A$100000, ">=" & DATE('Cash flow'!$E$3, 1, 1), 'List Expenses'!$A$3:$A$100000, "<" & DATE('Cash flow'!$E$3, 2, 1)) -> 0
C29: Groceries | D29: =SUMIFS('List Expenses'!$C$3:$C$100000, 'List Expenses'!$B$3:$B$100000, 'Yearly expenses'!$C7, 'List Expenses'!$A$3:$A$100000, ">=" & DATE('Cash flow'!$E$3, 1, 1), 'List Expenses'!$A$3:$A$100000, "<" & DATE('Cash flow'!$E$3, 2, 1)) -> 0
C30: Pre-paid card | D30: =SUMIFS('List Expenses'!$C$3:$C$100000, 'List Expenses'!$B$3:$B$100000, 'Yearly expenses'!$C8, 'List Expenses'!$A$3:$A$100000, ">=" & DATE('Cash flow'!$E$3, 1, 1), 'List Expenses'!$A$3:$A$100000, "<" & DATE('Cash flow'!$E$3, 2, 1)) -> 0
C31: Going out | D31: =SUMIFS('List Expenses'!$C$3:$C$100000, 'List Expenses'!$B$3:$B$100000, 'Yearly expenses'!$C9, 'List Expenses'!$A$3:$A$100000, ">=" & DATE('Cash flow'!$E$3, 1, 1), 'List Expenses'!$A$3:$A$100000, "<" & DATE('Cash flow'!$E$3, 2, 1)) -> 0
C32: Claudia | D32: =SUMIFS('List Expenses'!$C$3:$C$100000, 'List Expenses'!$B$3:$B$100000, 'Yearly expenses'!$C10, 'List Expenses'!$A$3:$A$100000, ">=" & DATE('Cash flow'!$E$3, 1, 1), 'List Expenses'!$A$3:$A$100000, "<" & DATE('Cash flow'!$E$3, 2, 1)) -> 0
C33: Family | D33: =SUMIFS('List Expenses'!$C$3:$C$100000, 'List Expenses'!$B$3:$B$100000, 'Yearly expenses'!$C11, 'List Expenses'!$A$3:$A$100000, ">=" & DATE('Cash flow'!$E$3, 1, 1), 'List Expenses'!$A$3:$A$100000, "<" & DATE('Cash flow'!$E$3, 2, 1)) -> 0
C34: Shopping | D34: =SUMIFS('List Expenses'!$C$3:$C$100000, 'List Expenses'!$B$3:$B$100000, 'Yearly expenses'!$C12, 'List Expenses'!$A$3:$A$100000, ">=" & DATE('Cash flow'!$E$3, 1, 1), 'List Expenses'!$A$3:$A$100000, "<" & DATE('Cash flow'!$E$3, 2, 1)) -> 0
C35: Transportation | D35: =SUMIFS('List Expenses'!$C$3:$C$100000, 'List Expenses'!$B$3:$B$100000, 'Yearly expenses'!$C13, 'List Expenses'!$A$3:$A$100000, ">=" & DATE('Cash flow'!$E$3, 1, 1), 'List Expenses'!$A$3:$A$100000, "<" & DATE('Cash flow'!$E$3, 2, 1)) -> 0
C36: Personal care | D36: =SUMIFS('List Expenses'!$C$3:$C$100000, 'List Expenses'!$B$3:$B$100000, 'Yearly expenses'!$C14, 'List Expenses'!$A$3:$A$100000, ">=" & DATE('Cash flow'!$E$3, 1, 1), 'List Expenses'!$A$3:$A$100000, "<" & DATE('Cash flow'!$E$3, 2, 1)) -> 0
C37: Credit cards | D37: =SUMIFS('List Expenses'!$C$3:$C$100000, 'List Expenses'!$B$3:$B$100000, 'Yearly expenses'!$C15, 'List Expenses'!$A$3:$A$100000, ">=" & DATE('Cash flow'!$E$3, 1, 1), 'List Expenses'!$A$3:$A$100000, "<" & DATE('Cash flow'!$E$3, 2, 1)) -> 0
C38: Gifts / Charity | D38: =SUMIFS('List Expenses'!$C$3:$C$100000, 'List Expenses'!$B$3:$B$100000, 'Yearly expenses'!$C16, 'List Expenses'!$A$3:$A$100000, ">=" & DATE('Cash flow'!$E$3, 1, 1), 'List Expenses'!$A$3:$A$100000, "<" & DATE('Cash flow'!$E$3, 2, 1)) -> 0
C39: Travel | D39: =SUMIFS('List Expenses'!$C$3:$C$100000, 'List Expenses'!$B$3:$B$100000, 'Yearly expenses'!$C17, 'List Expenses'!$A$3:$A$100000, ">=" & DATE('Cash flow'!$E$3, 1, 1), 'List Expenses'!$A$3:$A$100000, "<" & DATE('Cash flow'!$E$3, 2, 1)) -> 0
... C41: Other | D41: =SUMIFS('List Expenses'!$C$3:$C$100000, 'List Expenses'!$B$3:$B$100000, 'Yearly expenses'!$C19, 'List Expenses'!$A$3:$A$100000, ">=" & DATE('Cash flow'!$E$3, 1, 1), 'List Expenses'!$A$3:$A$100000, "<" & DATE('Cash flow'!$E$3, 2, 1)) -> 0
C42: Total expenses | D42: =SUBTOTAL(109,Expenses2[Actual]) -> 0
C46: February EXPENSES
C48: Monthly expenses | D48: Actual
C49: Restaurants | D49: =SUMIFS('List Expenses'!$C$3:$C$100000, 'List Expenses'!$B$3:$B$100000, 'Yearly expenses'!$C6, 'List Expenses'!$A$3:$A$100000, ">=" & DATE('Cash flow'!$E$3, 2, 1), 'List Expenses'!$A$3:$A$100000, "<" & DATE('Cash flow'!$E$3, 3, 1)) -> 0
C50: Groceries | D50: =SUMIFS('List Expenses'!$C$3:$C$100000, 'List Expenses'!$B$3:$B$100000, 'Yearly expenses'!$C7, 'List Expenses'!$A$3:$A$100000, ">=" & DATE('Cash flow'!$E$3, 2, 1), 'List Expenses'!$A$3:$A$100000, "<" & DATE('Cash flow'!$E$3, 3, 1)) -> 0
C51: Pre-paid card | D51: =SUMIFS('List Expenses'!$C$3:$C$100000, 'List Expenses'!$B$3:$B$100000, 'Yearly expenses'!$C8, 'List Expenses'!$A$3:$A$100000, ">=" & DATE('Cash flow'!$E$3, 2, 1), 'List Expenses'!$A$3:$A$100000, "<" & DATE('Cash flow'!$E$3, 3, 1)) -> 0
C52: Going out | D52: =SUMIFS('List Expenses'!$C$3:$C$100000, 'List Expenses'!$B$3:$B$100000, 'Yearly expenses'!$C9, 'List Expenses'!$A$3:$A$100000, ">=" & DATE('Cash flow'!$E$3, 2, 1), 'List Expenses'!$A$3:$A$100000, "<" & DATE('Cash flow'!$E$3, 3, 1)) -> 0
C53: Claudia | D53: =SUMIFS('List Expenses'!$C$3:$C$100000, 'List Expenses'!$B$3:$B$100000, 'Yearly expenses'!$C10, 'List Expenses'!$A$3:$A$100000, ">=" & DATE('Cash flow'!$E$3, 2, 1), 'List Expenses'!$A$3:$A$100000, "<" & DATE('Cash flow'!$E$3, 3, 1)) -> 0
C54: Family | D54: =SUMIFS('List Expenses'!$C$3:$C$100000, 'List Expenses'!$B$3:$B$100000, 'Yearly expenses'!$C11, 'List Expenses'!$A$3:$A$100000, ">=" & DATE('Cash flow'!$E$3, 2, 1), 'List Expenses'!$A$3:$A$100000, "<" & DATE('Cash flow'!$E$3, 3, 1)) -> 0
C55: Shopping | D55: =SUMIFS('List Expenses'!$C$3:$C$100000, 'List Expenses'!$B$3:$B$100000, 'Yearly expenses'!$C12, 'List Expenses'!$A$3:$A$100000, ">=" & DATE('Cash flow'!$E$3, 2, 1), 'List Expenses'!$A$3:$A$100000, "<" & DATE('Cash flow'!$E$3, 3, 1)) -> 0
C56: Transportation | D56: =SUMIFS('List Expenses'!$C$3:$C$100000, 'List Expenses'!$B$3:$B$100000, 'Yearly expenses'!$C13, 'List Expenses'!$A$3:$A$100000, ">=" & DATE('Cash flow'!$E$3, 2, 1), 'List Expenses'!$A$3:$A$100000, "<" & DATE('Cash flow'!$E$3, 3, 1)) -> 0
C57: Personal care | D57: =SUMIFS('List Expenses'!$C$3:$C$100000, 'List Expenses'!$B$3:$B$100000, 'Yearly expenses'!$C14, 'List Expenses'!$A$3:$A$100000, ">=" & DATE('Cash flow'!$E$3, 2, 1), 'List Expenses'!$A$3:$A$100000, "<" & DATE('Cash flow'!$E$3, 3, 1)) -> 0
C58: Credit cards | D58: =SUMIFS('List Expenses'!$C$3:$C$100000, 'List Expenses'!$B$3:$B$100000, 'Yearly expenses'!$C15, 'List Expenses'!$A$3:$A$100000, ">=" & DATE('Cash flow'!$E$3, 2, 1), 'List Expenses'!$A$3:$A$100000, "<" & DATE('Cash flow'!$E$3, 3, 1)) -> 0
C59: Gifts / Charity | D59: =SUMIFS('List Expenses'!$C$3:$C$100000, 'List Expenses'!$B$3:$B$100000, 'Yearly expenses'!$C16, 'List Expenses'!$A$3:$A$100000, ">=" & DATE('Cash flow'!$E$3, 2, 1), 'List Expenses'!$A$3:$A$100000, "<" & DATE('Cash flow'!$E$3, 3, 1)) -> 0
C60: Travel | D60: =SUMIFS('List Expenses'!$C$3:$C$100000, 'List Expenses'!$B$3:$B$100000, 'Yearly expenses'!$C17, 'List Expenses'!$A$3:$A$100000, ">=" & DATE('Cash flow'!$E$3, 2, 1), 'List Expenses'!$A$3:$A$100000, "<" & DATE('Cash flow'!$E$3, 3, 1)) -> 0
... C62: Other | D62: =SUMIFS('List Expenses'!$C$3:$C$100000, 'List Expenses'!$B$3:$B$100000, 'Yearly expenses'!$C19, 'List Expenses'!$A$3:$A$100000, ">=" & DATE('Cash flow'!$E$3, 2, 1), 'List Expenses'!$A$3:$A$100000, "<" & DATE('Cash flow'!$E$3, 3, 1)) -> 0
C63: Total expenses | D63: =SUBTOTAL(109,Expenses4[Actual]) -> 0
C67: March EXPENSES
C69: Monthly expenses | D69: Actual
C70: Restaurants | D70: =SUMIFS('List Expenses'!$C$3:$C$100000, 'List Expenses'!$B$3:$B$100000, 'Yearly expenses'!$C6, 'List Expenses'!$A$3:$A$100000, ">=" & DATE('Cash flow'!$E$3, 3, 1), 'List Expenses'!$A$3:$A$100000, "<" & DATE('Cash flow'!$E$3, 4, 1)) -> 0
C71: Groceries | D71: =SUMIFS('List Expenses'!$C$3:$C$100000, 'List Expenses'!$B$3:$B$100000, 'Yearly expenses'!$C7, 'List Expenses'!$A$3:$A$100000, ">=" & DATE('Cash flow'!$E$3, 3, 1), 'List Expenses'!$A$3:$A$100000, "<" & DATE('Cash flow'!$E$3, 4, 1)) -> 0
C72: Pre-paid card | D72: =SUMIFS('List Expenses'!$C$3:$C$100000, 'List Expenses'!$B$3:$B$100000, 'Yearly expenses'!$C8, 'List Expenses'!$A$3:$A$100000, ">=" & DATE('Cash flow'!$E$3, 3, 1), 'List Expenses'!$A$3:$A$100000, "<" & DATE('Cash flow'!$E$3, 4, 1)) -> 0
C73: Going out | D73: =SUMIFS('List Expenses'!$C$3:$C$100000, 'List Expenses'!$B$3:$B$100000, 'Yearly expenses'!$C9, 'List Expenses'!$A$3:$A$100000, ">=" & DATE('Cash flow'!$E$3, 3, 1), 'List Expenses'!$A$3:$A$100000, "<" & DATE('Cash flow'!$E$3, 4, 1)) -> 0
C74: Claudia | D74: =SUMIFS('List Expenses'!$C$3:$C$100000, 'List Expenses'!$B$3:$B$100000, 'Yearly expenses'!$C10, 'List Expenses'!$A$3:$A$100000, ">=" & DATE('Cash flow'!$E$3, 3, 1), 'List Expenses'!$A$3:$A$100000, "<" & DATE('Cash flow'!$E$3, 4, 1)) -> 0
C75: Family | D75: =SUMIFS('List Expenses'!$C$3:$C$100000, 'List Expenses'!$B$3:$B$100000, 'Yearly expenses'!$C11, 'List Expenses'!$A$3:$A$100000, ">=" & DATE('Cash flow'!$E$3, 3, 1), 'List Expenses'!$A$3:$A$100000, "<" & DATE('Cash flow'!$E$3, 4, 1)) -> 0
C76: Shopping | D76: =SUMIFS('List Expenses'!$C$3:$C$100000, 'List Expenses'!$B$3:$B$100000, 'Yearly expenses'!$C12, 'List Expenses'!$A$3:$A$100000, ">=" & DATE('Cash flow'!$E$3, 3, 1), 'List Expenses'!$A$3:$A$100000, "<" & DATE('Cash flow'!$E$3, 4, 1)) -> 0
C77: Transportation | D77: =SUMIFS('List Expenses'!$C$3:$C$100000, 'List Expenses'!$B$3:$B$100000, 'Yearly expenses'!$C13, 'List Expenses'!$A$3:$A$100000, ">=" & DATE('Cash flow'!$E$3, 3, 1), 'List Expenses'!$A$3:$A$100000, "<" & DATE('Cash flow'!$E$3, 4, 1)) -> 0
C78: Personal care | D78: =SUMIFS('List Expenses'!$C$3:$C$100000, 'List Expenses'!$B$3:$B$100000, 'Yearly expenses'!$C14, 'List Expenses'!$A$3:$A$100000, ">=" & DATE('Cash flow'!$E$3, 3, 1), 'List Expenses'!$A$3:$A$100000, "<" & DATE('Cash flow'!$E$3, 4, 1)) -> 0
C79: Credit cards | D79: =SUMIFS('List Expenses'!$C$3:$C$100000, 'List Expenses'!$B$3:$B$100000, 'Yearly expenses'!$C15, 'List Expenses'!$A$3:$A$100000, ">=" & DATE('Cash flow'!$E$3, 3, 1), 'List Expenses'!$A$3:$A$100000, "<" & DATE('Cash flow'!$E$3, 4, 1)) -> 0
C80: Gifts / Charity | D80: =SUMIFS('List Expenses'!$C$3:$C$100000, 'List Expenses'!$B$3:$B$100000, 'Yearly expenses'!$C16, 'List Expenses'!$A$3:$A$100000, ">=" & DATE('Cash flow'!$E$3, 3, 1), 'List Expenses'!$A$3:$A$100000, "<" & DATE('Cash flow'!$E$3, 4, 1)) -> 0
C81: Travel | D81: =SUMIFS('List Expenses'!$C$3:$C$100000, 'List Expenses'!$B$3:$B$100000, 'Yearly expenses'!$C17, 'List Expenses'!$A$3:$A$100000, ">=" & DATE('Cash flow'!$E$3, 3, 1), 'List Expenses'!$A$3:$A$100000, "<" & DATE('Cash flow'!$E$3, 4, 1)) -> 0
... C83: Other | D83: =SUMIFS('List Expenses'!$C$3:$C$100000, 'List Expenses'!$B$3:$B$100000, 'Yearly expenses'!$C19, 'List Expenses'!$A$3:$A$100000, ">=" & DATE('Cash flow'!$E$3, 3, 1), 'List Expenses'!$A$3:$A$100000, "<" & DATE('Cash flow'!$E$3, 4, 1)) -> 0
C84: Total expenses | D84: =SUBTOTAL(109,Expenses5[Actual]) -> 0
C88: April EXPENSES
C90: Monthly expenses | D90: Actual
C91: Restaurants | D91: =SUMIFS('List Expenses'!$C$3:$C$100000, 'List Expenses'!$B$3:$B$100000, 'Yearly expenses'!$C27, 'List Expenses'!$A$3:$A$100000, ">=" & DATE('Cash flow'!$E$3, 4, 1), 'List Expenses'!$A$3:$A$100000, "<" & DATE('Cash flow'!$E$3, 5, 1)) -> 0
C92: Groceries | D92: =SUMIFS('List Expenses'!$C$3:$C$100000, 'List Expenses'!$B$3:$B$100000, 'Yearly expenses'!$C28, 'List Expenses'!$A$3:$A$100000, ">=" & DATE('Cash flow'!$E$3, 4, 1), 'List Expenses'!$A$3:$A$100000, "<" & DATE('Cash flow'!$E$3, 5, 1)) -> 0
C93: Pre-paid card | D93: =SUMIFS('List Expenses'!$C$3:$C$100000, 'List Expenses'!$B$3:$B$100000, 'Yearly expenses'!$C29, 'List Expenses'!$A$3:$A$100000, ">=" & DATE('Cash flow'!$E$3, 4, 1), 'List Expenses'!$A$3:$A$100000, "<" & DATE('Cash flow'!$E$3, 5, 1)) -> 0
C94: Going out | D94: =SUMIFS('List Expenses'!$C$3:$C$100000, 'List Expenses'!$B$3:$B$100000, 'Yearly expenses'!$C30, 'List Expenses'!$A$3:$A$100000, ">=" & DATE('Cash flow'!$E$3, 4, 1), 'List Expenses'!$A$3:$A$100000, "<" & DATE('Cash flow'!$E$3, 5, 1)) -> 0
C95: Claudia | D95: =SUMIFS('List Expenses'!$C$3:$C$100000, 'List Expenses'!$B$3:$B$100000, 'Yearly expenses'!$C31, 'List Expenses'!$A$3:$A$100000, ">=" & DATE('Cash flow'!$E$3, 4, 1), 'List Expenses'!$A$3:$A$100000, "<" & DATE('Cash flow'!$E$3, 5, 1)) -> 0
C96: Family | D96: =SUMIFS('List Expenses'!$C$3:$C$100000, 'List Expenses'!$B$3:$B$100000, 'Yearly expenses'!$C32, 'List Expenses'!$A$3:$A$100000, ">=" & DATE('Cash flow'!$E$3, 4, 1), 'List Expenses'!$A$3:$A$100000, "<" & DATE('Cash flow'!$E$3, 5, 1)) -> 0
C97: Shopping | D97: =SUMIFS('List Expenses'!$C$3:$C$100000, 'List Expenses'!$B$3:$B$100000, 'Yearly expenses'!$C33, 'List Expenses'!$A$3:$A$100000, ">=" & DATE('Cash flow'!$E$3, 4, 1), 'List Expenses'!$A$3:$A$100000, "<" & DATE('Cash flow'!$E$3, 5, 1)) -> 0
C98: Transportation | D98: =SUMIFS('List Expenses'!$C$3:$C$100000, 'List Expenses'!$B$3:$B$100000, 'Yearly expenses'!$C34, 'List Expenses'!$A$3:$A$100000, ">=" & DATE('Cash flow'!$E$3, 4, 1), 'List Expenses'!$A$3:$A$100000, "<" & DATE('Cash flow'!$E$3, 5, 1)) -> 0
C99: Personal care | D99: =SUMIFS('List Expenses'!$C$3:$C$100000, 'List Expenses'!$B$3:$B$100000, 'Yearly expenses'!$C35, 'List Expenses'!$A$3:$A$100000, ">=" & DATE('Cash flow'!$E$3, 4, 1), 'List Expenses'!$A$3:$A$100000, "<" & DATE('Cash flow'!$E$3, 5, 1)) -> 0
C100: Credit cards | D100: =SUMIFS('List Expenses'!$C$3:$C$100000, 'List Expenses'!$B$3:$B$100000, 'Yearly expenses'!$C36, 'List Expenses'!$A$3:$A$100000, ">=" & DATE('Cash flow'!$E$3, 4, 1), 'List Expenses'!$A$3:$A$100000, "<" & DATE('Cash flow'!$E$3, 5, 1)) -> 0
C101: Gifts / Charity | D101: =SUMIFS('List Expenses'!$C$3:$C$100000, 'List Expenses'!$B$3:$B$100000, 'Yearly expenses'!$C37, 'List Expenses'!$A$3:$A$100000, ">=" & DATE('Cash flow'!$E$3, 4, 1), 'List Expenses'!$A$3:$A$100000, "<" & DATE('Cash flow'!$E$3, 5, 1)) -> 0
C102: Travel | D102: =SUMIFS('List Expenses'!$C$3:$C$100000, 'List Expenses'!$B$3:$B$100000, 'Yearly expenses'!$C38, 'List Expenses'!$A$3:$A$100000, ">=" & DATE('Cash flow'!$E$3, 4, 1), 'List Expenses'!$A$3:$A$100000, "<" & DATE('Cash flow'!$E$3, 5, 1)) -> 0
... C104: Other | D104: =SUMIFS('List Expenses'!$C$3:$C$100000, 'List Expenses'!$B$3:$B$100000, 'Yearly expenses'!$C40, 'List Expenses'!$A$3:$A$100000, ">=" & DATE('Cash flow'!$E$3, 4, 1), 'List Expenses'!$A$3:$A$100000, "<" & DATE('Cash flow'!$E$3, 5, 1)) -> 0
C105: Total expenses | D105: =SUBTOTAL(109,Expenses517[Actual]) -> 0
C109: May EXPENSES
C111: Monthly expenses | D111: Actual
C112: Restaurants | D112: =SUMIFS('List Expenses'!$C$3:$C$100000, 'List Expenses'!$B$3:$B$100000, 'Yearly expenses'!$C48, 'List Expenses'!$A$3:$A$100000, ">=" & DATE('Cash flow'!$E$3, 5, 1), 'List Expenses'!$A$3:$A$100000, "<" & DATE('Cash flow'!$E$3, 6, 1)) -> 0
C113: Groceries | D113: =SUMIFS('List Expenses'!$C$3:$C$100000, 'List Expenses'!$B$3:$B$100000, 'Yearly expenses'!$C49, 'List Expenses'!$A$3:$A$100000, ">=" & DATE('Cash flow'!$E$3, 5, 1), 'List Expenses'!$A$3:$A$100000, "<" & DATE('Cash flow'!$E$3, 6, 1)) -> 0
C114: Pre-paid card | D114: =SUMIFS('List Expenses'!$C$3:$C$100000, 'List Expenses'!$B$3:$B$100000, 'Yearly expenses'!$C50, 'List Expenses'!$A$3:$A$100000, ">=" & DATE('Cash flow'!$E$3, 5, 1), 'List Expenses'!$A$3:$A$100000, "<" & DATE('Cash flow'!$E$3, 6, 1)) -> 0
C115: Going out | D115: =SUMIFS('List Expenses'!$C$3:$C$100000, 'List Expenses'!$B$3:$B$100000, 'Yearly expenses'!$C51, 'List Expenses'!$A$3:$A$100000, ">=" & DATE('Cash flow'!$E$3, 5, 1), 'List Expenses'!$A$3:$A$100000, "<" & DATE('Cash flow'!$E$3, 6, 1)) -> 0
C116: Claudia | D116: =SUMIFS('List Expenses'!$C$3:$C$100000, 'List Expenses'!$B$3:$B$100000, 'Yearly expenses'!$C52, 'List Expenses'!$A$3:$A$100000, ">=" & DATE('Cash flow'!$E$3, 5, 1), 'List Expenses'!$A$3:$A$100000, "<" & DATE('Cash flow'!$E$3, 6, 1)) -> 0
C117: Family | D117: =SUMIFS('List Expenses'!$C$3:$C$100000, 'List Expenses'!$B$3:$B$100000, 'Yearly expenses'!$C53, 'List Expenses'!$A$3:$A$100000, ">=" & DATE('Cash flow'!$E$3, 5, 1), 'List Expenses'!$A$3:$A$100000, "<" & DATE('Cash flow'!$E$3, 6, 1)) -> 0
C118: Shopping | D118: =SUMIFS('List Expenses'!$C$3:$C$100000, 'List Expenses'!$B$3:$B$100000, 'Yearly expenses'!$C54, 'List Expenses'!$A$3:$A$100000, ">=" & DATE('Cash flow'!$E$3, 5, 1), 'List Expenses'!$A$3:$A$100000, "<" & DATE('Cash flow'!$E$3, 6, 1)) -> 0
C119: Transportation | D119: =SUMIFS('List Expenses'!$C$3:$C$100000, 'List Expenses'!$B$3:$B$100000, 'Yearly expenses'!$C55, 'List Expenses'!$A$3:$A$100000, ">=" & DATE('Cash flow'!$E$3, 5, 1), 'List Expenses'!$A$3:$A$100000, "<" & DATE('Cash flow'!$E$3, 6, 1)) -> 0
C120: Personal care | D120: =SUMIFS('List Expenses'!$C$3:$C$100000, 'List Expenses'!$B$3:$B$100000, 'Yearly expenses'!$C56, 'List Expenses'!$A$3:$A$100000, ">=" & DATE('Cash flow'!$E$3, 5, 1), 'List Expenses'!$A$3:$A$100000, "<" & DATE('Cash flow'!$E$3, 6, 1)) -> 0
C121: Credit cards | D121: =SUMIFS('List Expenses'!$C$3:$C$100000, 'List Expenses'!$B$3:$B$100000, 'Yearly expenses'!$C57, 'List Expenses'!$A$3:$A$100000, ">=" & DATE('Cash flow'!$E$3, 5, 1), 'List Expenses'!$A$3:$A$100000, "<" & DATE('Cash flow'!$E$3, 6, 1)) -> 0
C122: Gifts / Charity | D122: =SUMIFS('List Expenses'!$C$3:$C$100000, 'List Expenses'!$B$3:$B$100000, 'Yearly expenses'!$C58, 'List Expenses'!$A$3:$A$100000, ">=" & DATE('Cash flow'!$E$3, 5, 1), 'List Expenses'!$A$3:$A$100000, "<" & DATE('Cash flow'!$E$3, 6, 1)) -> 0
C123: Travel | D123: =SUMIFS('List Expenses'!$C$3:$C$100000, 'List Expenses'!$B$3:$B$100000, 'Yearly expenses'!$C59, 'List Expenses'!$A$3:$A$100000, ">=" & DATE('Cash flow'!$E$3, 5, 1), 'List Expenses'!$A$3:$A$100000, "<" & DATE('Cash flow'!$E$3, 6, 1)) -> 0
... C125: Other | D125: =SUMIFS('List Expenses'!$C$3:$C$100000, 'List Expenses'!$B$3:$B$100000, 'Yearly expenses'!$C61, 'List Expenses'!$A$3:$A$100000, ">=" & DATE('Cash flow'!$E$3, 5, 1), 'List Expenses'!$A$3:$A$100000, "<" & DATE('Cash flow'!$E$3, 6, 1)) -> 0
C126: Total expenses | D126: =SUBTOTAL(109,Expenses520[Actual]) -> 0
C130: June EXPENSES
C132: Monthly expenses | D132: Actual
C133: Restaurants | D133: =SUMIFS('List Expenses'!$C$3:$C$100000, 'List Expenses'!$B$3:$B$100000, 'Yearly expenses'!$C69, 'List Expenses'!$A$3:$A$100000, ">=" & DATE('Cash flow'!$E$3, 6, 1), 'List Expenses'!$A$3:$A$100000, "<" & DATE('Cash flow'!$E$3, 7, 1)) -> 0
C134: Groceries | D134: =SUMIFS('List Expenses'!$C$3:$C$100000, 'List Expenses'!$B$3:$B$100000, 'Yearly expenses'!$C70, 'List Expenses'!$A$3:$A$100000, ">=" & DATE('Cash flow'!$E$3, 6, 1), 'List Expenses'!$A$3:$A$100000, "<" & DATE('Cash flow'!$E$3, 7, 1)) -> 0
...

Sheet List Income
A1: DATE | B1: CATEGORY | C1: AMOUT | D1: DESCRIPTION

Sheet List Expenses
A1: DATE | B1: CATEGORY | C1: AMOUNT | D1: DESCRIPTION
